graphscope_runtime/__init__.py
gs_apps.libs/libgomp-a34b3233.so.1.0.0
gs_apps-0.29.0.dist-info/METADATA
gs_apps-0.29.0.dist-info/RECORD
gs_apps-0.29.0.dist-info/top_level.txt
gs_apps-0.29.0.dist-info/WHEEL
graphscope.runtime/precompiled/builtin/3d51759d5416e2cdc86a037c838414cdeb2860f02b6ede0f1d7e59749daa7716/lib3d51759d5416e2cdc86a037c838414cdeb2860f02b6ede0f1d7e59749daa7716.so
graphscope.runtime/precompiled/builtin/3d51759d5416e2cdc86a037c838414cdeb2860f02b6ede0f1d7e59749daa7716/Makefile
graphscope.runtime/precompiled/builtin/3d51759d5416e2cdc86a037c838414cdeb2860f02b6ede0f1d7e59749daa7716/CMakeCache.txt
graphscope.runtime/precompiled/builtin/3d51759d5416e2cdc86a037c838414cdeb2860f02b6ede0f1d7e59749daa7716/CMakeLists.txt
graphscope.runtime/precompiled/builtin/3d51759d5416e2cdc86a037c838414cdeb2860f02b6ede0f1d7e59749daa7716/cmake_install.cmake
graphscope.runtime/precompiled/builtin/c71a1d567a61160da4137e9795a33c263e86a0e77b37f5693a906f3daa1f5b36/Makefile
graphscope.runtime/precompiled/builtin/c71a1d567a61160da4137e9795a33c263e86a0e77b37f5693a906f3daa1f5b36/libc71a1d567a61160da4137e9795a33c263e86a0e77b37f5693a906f3daa1f5b36.so
graphscope.runtime/precompiled/builtin/c71a1d567a61160da4137e9795a33c263e86a0e77b37f5693a906f3daa1f5b36/CMakeCache.txt
graphscope.runtime/precompiled/builtin/c71a1d567a61160da4137e9795a33c263e86a0e77b37f5693a906f3daa1f5b36/CMakeLists.txt
graphscope.runtime/precompiled/builtin/c71a1d567a61160da4137e9795a33c263e86a0e77b37f5693a906f3daa1f5b36/cmake_install.cmake
graphscope.runtime/precompiled/builtin/45f302e1c4f8e63f085ec282ea079a5e428491c209fb8e9fe7aa2c409335c5a9/Makefile
graphscope.runtime/precompiled/builtin/45f302e1c4f8e63f085ec282ea079a5e428491c209fb8e9fe7aa2c409335c5a9/CMakeCache.txt
graphscope.runtime/precompiled/builtin/45f302e1c4f8e63f085ec282ea079a5e428491c209fb8e9fe7aa2c409335c5a9/CMakeLists.txt
graphscope.runtime/precompiled/builtin/45f302e1c4f8e63f085ec282ea079a5e428491c209fb8e9fe7aa2c409335c5a9/cmake_install.cmake
